NAVIAI4/JetsonNano.cpython-36m-aarch64-linux-gnu.so
NAVIAI4/__init__.py
escaper_temp/__init__.py
escaper_utilities/__init__.py
escaper_utils/__init__.py
NAVIAI4-1.0.10.dist-info/METADATA
NAVIAI4-1.0.10.dist-info/WHEEL
NAVIAI4-1.0.10.dist-info/top_level.txt
NAVIAI4-1.0.10.dist-info/RECORD
