Metadata-Version: 2.1
Name: NAVIAI4
Version: 1.0.10
Summary: NAVIAI4
Home-page: 
Download-URL: 
Author: sike6054
Author-email: sike6054@gmail.com
Classifier: Programming Language :: Python :: 3.6
Requires-Python: ~=3.6
